LICENSE
MANIFEST.in
README.md
pyproject.toml
setup.py
ladi/__init__.py
ladi/_ext.pyx
ladi/ladi.py
ladi/mat.py
ladi/preprocess.py
ladi.egg-info/PKG-INFO
ladi.egg-info/SOURCES.txt
ladi.egg-info/dependency_links.txt
ladi.egg-info/requires.txt
ladi.egg-info/top_level.txt
ladi/ladi/ladi.c
ladi/ladi/ladi.h
ladi/mat/mat.c
ladi/mat/mat.h
ladi/pinv/pinv.c
ladi/pinv/pinv.h
tests/test_ladi.py
tests/test_mat.py
tests/test_preprocess.py