Metadata-Version: 2.1
Name: ladi
Version: 0.0.1
Summary: Fast multi-threaded high-spatial, high-temporal interpolation
Home-page: https://github.com/asenogles/ladi
Author: asenogles
License: BSD
Requires-Python: >=3.6
License-File: LICENSE
